vira/__init__.py
vira/display_win.py
vira/gui.py
vira-1.0.2.dist-info/METADATA
vira-1.0.2.dist-info/WHEEL
vira-1.0.2.dist-info/entry_points.txt
vira-1.0.2.dist-info/top_level.txt
vira-1.0.2.dist-info/RECORD
