Metadata-Version: 2.1
Name: vira
Version: 1.0.2
Summary: A Calculator for Calculating
Home-page: UNKNOWN
Author: GN Vageesh
Author-email: vageeshgn2005@gmail.com
Maintainer: GN Vageesh
Maintainer-email: vageeshgn2005@gmail.com
License: MIT
Download-URL: https://github.com/GNVageesh/vira
Keywords: python,python3,details,math,calculator,data,research,gui
Platform: UNKNOWN
Classifier: License :: OSI Approved :: MIT License
Classifier: Intended Audience :: Developers
Classifier: Operating System :: Unix
Classifier: Operating System :: MacOS :: MacOS X
Classifier: Operating System :: Microsoft :: Windows
Classifier: Programming Language :: Python :: 3
Classifier: Environment :: Console
Classifier: Development Status :: 5 - Production/Stable
Requires-Dist: PyQt5 (>=5.15.4)
